cosmocnc/__init__.py
cosmocnc/cat.py
cosmocnc/cnc.py
cosmocnc/cnc_cobaya_likelihood.py
cosmocnc/cnc_cobaya_theory.py
cosmocnc/config.py
cosmocnc/cosmo.py
cosmocnc/hmf.py
cosmocnc/params.py
cosmocnc/ps.py
cosmocnc/restore_nn.py
cosmocnc/sim.py
cosmocnc/sr.py
cosmocnc/utils.py
cosmocnc-1.0.dist-info/LICENSE.txt
cosmocnc-1.0.dist-info/METADATA
cosmocnc-1.0.dist-info/WHEEL
cosmocnc-1.0.dist-info/top_level.txt
cosmocnc-1.0.dist-info/RECORD
